autoa2a/__init__.py
autoa2a/cli.py
autoa2a/templates/agent_specific/crewai/agent.py.jinja2
autoa2a/templates/agent_specific/langgraph/agent.py.jinja2
autoa2a/templates/agent_specific/llama-index/agent.py.jinja2
autoa2a/templates/agent_specific/openai/agent.py.jinja2
autoa2a/templates/agent_specific/pydantic/agent.py.jinja2
autoa2a/templates/common/run_a2a.py.jinja2
autoa2a/templates/common/taskmanager.py.jinja2
common/__init__.py
common/types.py
common/client/__init__.py
common/client/card_resolver.py
common/client/client.py
common/server/__init__.py
common/server/server.py
common/server/task_manager.py
common/server/utils.py
common/utils/in_memory_cache.py
common/utils/push_notification_auth.py
autoa2a-0.0.3.dist-info/METADATA
autoa2a-0.0.3.dist-info/WHEEL
autoa2a-0.0.3.dist-info/entry_points.txt
autoa2a-0.0.3.dist-info/licenses/LICENSE
autoa2a-0.0.3.dist-info/RECORD
