Metadata-Version: 2.4
Name: autoa2a
Version: 0.0.3
Summary: Converts any agent into A2A servers
Project-URL: Homepage, https://github.com/NapthaAI/autoa2a
Author-email: Richard Blythman <richard@naptha.ai>
License:                                  Apache License
License-File: LICENSE
Requires-Python: >=3.12
Requires-Dist: click>=8.1.8
Requires-Dist: httpx-sse>=0.4.0
Requires-Dist: httpx>=0.28.1
Requires-Dist: jinja2>=3.1.6
Requires-Dist: jwcrypto>=1.5.6
Requires-Dist: pydantic>=2.10.6
Requires-Dist: pyjwt>=2.10.1
Requires-Dist: python-dotenv>=1.1.0
Requires-Dist: sse-starlette>=2.2.1
Requires-Dist: starlette>=0.46.1
Requires-Dist: typing-extensions>=4.12.2
Requires-Dist: uvicorn>=0.17.0
Requires-Dist: uvicorn>=0.34.0
